thuner/__init__.py
thuner/config.py
thuner/default.py
thuner/grid.py
thuner/log.py
thuner/parallel.py
thuner/utils.py
thuner/analyze/__init__.py
thuner/analyze/mcs.py
thuner/analyze/utils.py
thuner/attribute/__init__.py
thuner/attribute/attribute.py
thuner/attribute/core.py
thuner/attribute/ellipse.py
thuner/attribute/group.py
thuner/attribute/profile.py
thuner/attribute/quality.py
thuner/attribute/tag.py
thuner/attribute/utils.py
thuner/data/__init__.py
thuner/data/access.py
thuner/data/aura.py
thuner/data/dispatch.py
thuner/data/era5.py
thuner/data/gridrad.py
thuner/data/odim.py
thuner/data/synthetic.py
thuner/data/utils.py
thuner/data/wrf.py
thuner/detect/__init__.py
thuner/detect/detect.py
thuner/detect/preprocess.py
thuner/detect/steiner.py
thuner/group/__init__.py
thuner/group/group.py
thuner/match/__init__.py
thuner/match/box.py
thuner/match/correlate.py
thuner/match/match.py
thuner/match/object.py
thuner/match/tint.py
thuner/match/utils.py
thuner/option/__init__.py
thuner/option/attribute.py
thuner/option/data.py
thuner/option/grid.py
thuner/option/track.py
thuner/option/visualize.py
thuner/sql/__init__.py
thuner/test/__init__.py
thuner/test/demos_to_tests.py
thuner/test/test_cpol.py
thuner/test/test_gridrad.py
thuner/test/test_synthetic.py
thuner/track/__init__.py
thuner/track/track.py
thuner/track/utils.py
thuner/visualize/__init__.py
thuner/visualize/analysis.py
thuner/visualize/attribute.py
thuner/visualize/horizontal.py
thuner/visualize/runtime.py
thuner/visualize/utils.py
thuner/visualize/vertical.py
thuner/visualize/visualize.py
thuner/visualize/styles/__init__.py
thuner/visualize/styles/gadi.mplstyle
thuner/visualize/styles/paper.mplstyle
thuner/visualize/styles/presentation.mplstyle
thuner/write/__init__.py
thuner/write/attribute.py
thuner/write/filepath.py
thuner/write/mask.py
thuner/write/utils.py
thuner-0.0.16.dist-info/LICENSE.txt
thuner-0.0.16.dist-info/METADATA
thuner-0.0.16.dist-info/WHEEL
thuner-0.0.16.dist-info/top_level.txt
thuner-0.0.16.dist-info/RECORD
